equipt/__init__.py
equipt/analyzer.py
equipt/opener.py
equipt-1.0.2.dist-info/LICENSE
equipt-1.0.2.dist-info/METADATA
equipt-1.0.2.dist-info/WHEEL
equipt-1.0.2.dist-info/top_level.txt
equipt-1.0.2.dist-info/RECORD
