Metadata-Version: 2.1
Name: equipt
Version: 1.0.2
Summary: A suite of tools for quantitative PCR analysis
Author: Drew Honson
Author-email: honsonbiosci@gmail.com
Classifier: Programming Language :: Python :: 3
Classifier: Operating System :: OS Independent
License-File: LICENSE
